SantiagoCalc/__init__.py
SantiagoCalc/calculadora.py
santiagocalc-0.2.0.dist-info/licenses/LICENSE
santiagocalc-0.2.0.dist-info/METADATA
santiagocalc-0.2.0.dist-info/WHEEL
santiagocalc-0.2.0.dist-info/top_level.txt
santiagocalc-0.2.0.dist-info/RECORD
