Metadata-Version: 2.4
Name: SantiagoCalc
Version: 0.2.0
Summary: La mejor calculadora hecha en clase (por fin)
Author-email: Santiago Criollo Bermudez <santycb16@gmail.com>
License: Universidad Distrital FJC
Project-URL: Homepage, https://github.com/SanCriolloB/Desarrollo_Software.git
Requires-Python: >=3.8
License-File: LICENSE
Dynamic: license-file
